{
  "hash": "4b32f3e0",
  "configHash": "24ffb5a2",
  "lockfileHash": "2e56dbb3",
  "browserHash": "b096e713",
  "optimized": {
    "react": {
      "src": "../../node_modules/react/index.js",
      "file": "react.js",
      "fileHash": "9b053a0a",
      "needsInterop": true
    },
    "react-dom/client": {
      "src": "../../node_modules/react-dom/client.js",
      "file": "react-dom_client.js",
      "fileHash": "48e73c4d",
      "needsInterop": true
    },
    "react-icons/io5": {
      "src": "../../node_modules/react-icons/io5/index.mjs",
      "file": "react-icons_io5.js",
      "fileHash": "10f2a844",
      "needsInterop": false
    },
    "react-icons/fa": {
      "src": "../../node_modules/react-icons/fa/index.mjs",
      "file": "react-icons_fa.js",
      "fileHash": "48061107",
      "needsInterop": false
    },
    "react-icons/ri": {
      "src": "../../node_modules/react-icons/ri/index.mjs",
      "file": "react-icons_ri.js",
      "fileHash": "eb032872",
      "needsInterop": false
    },
    "react-icons/fa6": {
      "src": "../../node_modules/react-icons/fa6/index.mjs",
      "file": "react-icons_fa6.js",
      "fileHash": "6fa9163e",
      "needsInterop": false
    },
    "react-icons/tfi": {
      "src": "../../node_modules/react-icons/tfi/index.mjs",
      "file": "react-icons_tfi.js",
      "fileHash": "9945d9ce",
      "needsInterop": false
    }
  },
  "chunks": {
    "chunk-X6FNEU3M": {
      "file": "chunk-X6FNEU3M.js"
    },
    "chunk-GT27OAPC": {
      "file": "chunk-GT27OAPC.js"
    }
  }
}